{
  "MrtPathName": "Changi Airport Line",
  "color": [89, 167, 132],
  "path": [
    {
      "ADDRESS": "2 EXPO DRIVE EXPO MRT STATION SINGAPORE 485985",
      "BLK_NO": "2",
      "BUILDING": "EXPO MRT STATION",
      "LATITUDE": "1.33538252614957",
      "LONGITUDE": "103.962374747451",
      "LONGTITUDE": "103.962374747451",
      "POSTAL": "485985",
      "ROAD_NAME": "EXPO DRIVE",
      "SEARCHVAL": "EXPO MRT STATION",
      "X": "42362.6034600176",
      "Y": "35285.7083877865",
      "Station": "CG1",
      "Station Name": "Expo",
      "DISTRICT": "16",
      "coordinates": [103.962374747451, 1.33538252614957],
      "SUBZONE_NO": "5",
      "SUBZONE_N": "XILIN",
      "SUBZONE_C": "TMSZ05",
      "CA_IND": "N",
      "PLN_AREA_N": "TAMPINES",
      "PLN_AREA_C": "TM",
      "REGION_N": "EAST REGION",
      "REGION_C": "ER"
    },
    {
      "ADDRESS": "70 AIRPORT BOULEVARD CHANGI AIRPORT MRT STATION SINGAPORE 819661",
      "BLK_NO": "70",
      "BUILDING": "CHANGI AIRPORT MRT STATION",
      "LATITUDE": "1.35747897447696",
      "LONGITUDE": "103.98788356959",
      "LONGTITUDE": "103.98788356959",
      "POSTAL": "819661",
      "ROAD_NAME": "AIRPORT BOULEVARD",
      "SEARCHVAL": "CHANGI AIRPORT MRT STATION",
      "X": "45201.3203946929",
      "Y": "37729.1933764704",
      "Station": "CG2",
      "Station Name": "Changi Airport",
      "DISTRICT": "17",
      "coordinates": [103.98788356959, 1.35747897447696],
      "SUBZONE_NO": "3",
      "SUBZONE_N": "CHANGI AIRPORT",
      "SUBZONE_C": "CHSZ03",
      "CA_IND": "N",
      "PLN_AREA_N": "CHANGI",
      "PLN_AREA_C": "CH",
      "REGION_N": "EAST REGION",
      "REGION_C": "ER"
    }
  ]
}
